{".class": "MypyFile", "_fullname": "conf", "_name": null, "is_stub": false, "names": {".class": "SymbolTable", "__doc__": {".class": "SymbolTableNode", "kind": "Gdef", "node": {".class": "Var", "flags": ["is_ready"], "fullname": "conf.__doc__", "name": "__doc__", "type": {".class": "UnionType", "items": ["builtins.str", "builtins.unicode"]}}}, "__file__": {".class": "SymbolTableNode", "kind": "Gdef", "node": {".class": "Var", "flags": ["is_ready"], "fullname": "conf.__file__", "name": "__file__", "type": "builtins.str"}}, "__name__": {".class": "SymbolTableNode", "kind": "Gdef", "node": {".class": "Var", "flags": ["is_ready"], "fullname": "conf.__name__", "name": "__name__", "type": "builtins.str"}}, "__package__": {".class": "SymbolTableNode", "kind": "Gdef", "node": {".class": "Var", "flags": ["is_ready"], "fullname": "conf.__package__", "name": "__package__", "type": "builtins.str"}}, "html_extra_path": {".class": "SymbolTableNode", "kind": "Gdef", "node": {".class": "Var", "flags": [], "fullname": "conf.html_extra_path", "name": "html_extra_path", "type": {".class": "Instance", "args": ["builtins.str"], "type_ref": "builtins.list"}}}, "master_doc": {".class": "SymbolTableNode", "kind": "Gdef", "node": {".class": "Var", "flags": ["is_ready"], "fullname": "conf.master_doc", "name": "master_doc", "type": "builtins.str"}}, "source_suffix": {".class": "SymbolTableNode", "kind": "Gdef", "node": {".class": "Var", "flags": ["is_ready"], "fullname": "conf.source_suffix", "name": "source_suffix", "type": "builtins.str"}}, "subprocess": {".class": "SymbolTableNode", "cross_ref": "subprocess", "kind": "ModuleRef"}}, "path": "/Users/classner/git/forpy/docs/sphinx/conf.py"}
