{
 "identifier_static.index": {
  "documentation": "Integer identifier (enumeration index within a list)",
  "type": "static",
  "data_type": "INT_0D",
  "full_path": "identifier_static/index"
 },
 "identifier_static.description": {
  "documentation": "Verbose description",
  "type": "static",
  "data_type": "STR_0D",
  "full_path": "identifier_static/description"
 },
 "identifier_static.name": {
  "documentation": "Short string identifier",
  "type": "static",
  "data_type": "STR_0D",
  "full_path": "identifier_static/name"
 },
 "identifier_static": {
  "structure_reference": "self",
  "documentation": "Standard type for identifiers (static). The three fields: name, index and description are all representations of the same information. Associated with each application of this identifier-type, there should be a translation table defining the three fields for all objects to be identified.",
  "data_type": "structure",
  "full_path": "identifier_static"
 }
}