[{"model": "countries.countryname", "pk": 3112, "fields": {"country": "ST", "language": "deu", "common": "S\u00e3o Tom\u00e9 und Pr\u00edncipe", "official": "Demokratische Republik S\u00e3o Tom\u00e9 und Pr\u00edncipe"}}, {"model": "countries.countryname", "pk": 3125, "fields": {"country": "ST", "language": "eng", "common": "S\u00e3o Tom\u00e9 and Pr\u00edncipe", "official": "Democratic Republic of S\u00e3o Tom\u00e9 and Pr\u00edncipe"}}, {"model": "countries.countryname", "pk": 3123, "fields": {"country": "ST", "language": "est", "common": "S\u00e3o Tom\u00e9 ja Pr\u00edncipe", "official": "S\u00e3o Tom\u00e9 ja Pr\u00edncipe Demokraatlik Vabariik"}}, {"model": "countries.countryname", "pk": 3122, "fields": {"country": "ST", "language": "fin", "common": "S\u00e3o T\u00e9me ja Pr\u00edncipe", "official": "S\u00e3o Tom\u00e9 ja Pr\u00edncipen demokraattinen tasavalta"}}, {"model": "countries.countryname", "pk": 3113, "fields": {"country": "ST", "language": "fra", "common": "S\u00e3o Tom\u00e9 et Pr\u00edncipe", "official": "R\u00e9publique d\u00e9mocratique de S\u00e3o Tom\u00e9 et Pr\u00edncipe"}}, {"model": "countries.countryname", "pk": 3114, "fields": {"country": "ST", "language": "hrv", "common": "Sveti Toma i Princip", "official": "Demokratska Republika S\u00e3o Tome i Principe"}}, {"model": "countries.countryname", "pk": 3115, "fields": {"country": "ST", "language": "ita", "common": "S\u00e3o Tom\u00e9 e Pr\u00edncipe", "official": "Repubblica democratica di S\u00e3o Tom\u00e9 e Pr\u00edncipe"}}, {"model": "countries.countryname", "pk": 3116, "fields": {"country": "ST", "language": "jpn", "common": "\u30b5\u30f3\u30c8\u30e1\u30fb\u30d7\u30ea\u30f3\u30b7\u30da", "official": "\u30b5\u30f3\u30c8\u30e1\u00b7\u30d7\u30ea\u30f3\u30b7\u30da\u6c11\u4e3b\u5171\u548c\u56fd"}}, {"model": "countries.countryname", "pk": 3117, "fields": {"country": "ST", "language": "nld", "common": "Sao Tom\u00e9 en Principe", "official": "Democratische Republiek Sao Tom\u00e9 en Principe"}}, {"model": "countries.countryname", "pk": 3118, "fields": {"country": "ST", "language": "por", "common": "S\u00e3o Tom\u00e9 e Pr\u00edncipe", "official": "Rep\u00fablica Democr\u00e1tica do S\u00e3o Tom\u00e9 e Pr\u00edncipe"}}, {"model": "countries.countryname", "pk": 3120, "fields": {"country": "ST", "language": "rus", "common": "\u0421\u0430\u043d-\u0422\u043e\u043c\u0435 \u0438 \u041f\u0440\u0438\u043d\u0441\u0438\u043f\u0438", "official": "\u0414\u0435\u043c\u043e\u043a\u0440\u0430\u0442\u0438\u0447\u0435\u0441\u043a\u0430\u044f \u0420\u0435\u0441\u043f\u0443\u0431\u043b\u0438\u043a\u0430 \u0421\u0430\u043d-\u0422\u043e\u043c\u0435 \u0438 \u041f\u0440\u0438\u043d\u0441\u0438\u043f\u0438"}}, {"model": "countries.countryname", "pk": 3121, "fields": {"country": "ST", "language": "slk", "common": "Sv\u00e4t\u00fd Tom\u00e1\u0161 a Princov ostrov", "official": "Demokratick\u00e1 republika Sv\u00e4t\u00e9ho Tom\u00e1\u0161a A princovho ostrova"}}, {"model": "countries.countryname", "pk": 3119, "fields": {"country": "ST", "language": "spa", "common": "Santo Tom\u00e9 y Pr\u00edncipe", "official": "Rep\u00fablica Democr\u00e1tica de Santo Tom\u00e9 y Pr\u00edncipe"}}, {"model": "countries.countryname", "pk": 3124, "fields": {"country": "ST", "language": "zho", "common": "\u5723\u591a\u7f8e\u548c\u666e\u6797\u897f\u6bd4", "official": "\u5723\u591a\u7f8e\u548c\u666e\u6797\u897f\u6bd4\u6c11\u4e3b\u5171\u548c\u56fd"}}]