[{"model": "countries.division", "pk": 3804, "fields": {"country": "TM", "code": "A", "name": "Ahal", "alt_names": "[\"Akhal\"]", "location": "SRID=4326;POINT (59.4720904 38.6399398)", "bbox": "SRID=4326;POLYGON ((56.723392 35.58967, 56.723392 40.197323, 61.5114551 40.197323, 61.5114551 35.58967, 56.723392 35.58967))"}}, {"model": "countries.division", "pk": 3805, "fields": {"country": "TM", "code": "B", "name": "Balkan", "alt_names": "[\"Balkan\"]", "location": "SRID=4326;POINT (54.4952432 40.9468884)", "bbox": "SRID=4326;POLYGON ((52.4446017 37.309181, 52.4446017 42.3434979, 57.199726 42.3434979, 57.199726 37.309181, 52.4446017 37.309181))"}}, {"model": "countries.division", "pk": 3806, "fields": {"country": "TM", "code": "D", "name": "Dasoguz", "alt_names": "[\"Dashhovuz\", \"Dashhowuz\", \"Dashkhovuz\", \"Dashogus\", \"Dashoguz\", \"Da\\u015fhovuz\", \"Da\\u0161hovuz\", \"Tashauz\", \"Ta\\u0161auz\"]", "location": "SRID=4326;POINT (59.966667 41.833333)", "bbox": "SRID=4326;POLYGON ((59.8845004 41.788273, 59.8845004 41.880745, 60.038309 41.880745, 60.038309 41.788273, 59.8845004 41.788273))"}}, {"model": "countries.division", "pk": 3807, "fields": {"country": "TM", "code": "L", "name": "Lebap", "alt_names": "[\"Lebap\"]", "location": "SRID=4326;POINT (64.7162415 38.1272462)", "bbox": "SRID=4326;POLYGON ((60.1898739 36.850881, 60.1898739 41.2915379, 66.68430309999999 41.2915379, 66.68430309999999 36.850881, 60.1898739 36.850881))"}}, {"model": "countries.division", "pk": 3808, "fields": {"country": "TM", "code": "M", "name": "Mary", "alt_names": "[\"Mary\", \"Merv\"]", "location": "SRID=4326;POINT (62.4504154 36.9481623)", "bbox": "SRID=4326;POLYGON ((60.395035 35.141151, 60.395035 39.5136029, 64.73783899999999 39.5136029, 64.73783899999999 35.141151, 60.395035 35.141151))"}}, {"model": "countries.division", "pk": 3809, "fields": {"country": "TM", "code": "X~", "name": "", "alt_names": "[\"Ashgabat\", \"A\\u015fkabat\"]", "location": "SRID=4326;POINT (59.556278 38.969719)", "bbox": "SRID=4326;POLYGON ((52.4478449 35.12876, 52.4478449 42.798844, 66.707353 42.798844, 66.707353 35.12876, 52.4478449 35.12876))"}}]