[{"model": "countries.division", "pk": 4122, "fields": {"country": "UY", "code": "AR", "name": "Artigas", "alt_names": "[\"Artigas\"]", "location": "SRID=4326;POINT (-57.1013188 -30.4880891)", "bbox": "SRID=4326;POLYGON ((-57.888187 -31.054585, -57.888187 -30.082224, -55.9870069 -30.082224, -55.9870069 -31.054585, -57.888187 -31.054585))"}}, {"model": "countries.division", "pk": 4123, "fields": {"country": "UY", "code": "CA", "name": "Canelones", "alt_names": "[\"Canelones\"]", "location": null, "bbox": "SRID=4326;POLYGON ((-56.27778 -34.52278, -56.27778 -34.5166646, -56.2833322 -34.5166646, -56.2833322 -34.52278, -56.27778 -34.52278))"}}, {"model": "countries.division", "pk": 4125, "fields": {"country": "UY", "code": "CL", "name": "Cerro Lago", "alt_names": "[\"Cerro Lago\"]", "location": "SRID=4326;POINT (-54.1654 -32.3769)", "bbox": "SRID=4326;POLYGON ((-53.517 -32.36667, -53.517 -32.483, -54.18333 -32.483, -54.18333 -32.36667, -53.517 -32.36667))"}}, {"model": "countries.division", "pk": 4124, "fields": {"country": "UY", "code": "CO", "name": "Colonia", "alt_names": "[\"Colonia\"]", "location": "SRID=4326;POINT (-57.8339 -34.4607)", "bbox": "SRID=4326;POLYGON ((-56.7844 -35.5012, -56.7844 -34.4517, -57.7667 -34.4517, -57.7667 -35.5012, -56.7844 -35.5012))"}}, {"model": "countries.division", "pk": 4126, "fields": {"country": "UY", "code": "DU", "name": "Durazno", "alt_names": "[\"Durazno\"]", "location": "SRID=4326;POINT (-56.5275506 -33.3822982)", "bbox": "SRID=4326;POLYGON ((-56.6182749 -33.413685, -56.6182749 -33.3566481, -56.4953762 -33.3566481, -56.4953762 -33.413685, -56.6182749 -33.413685))"}}, {"model": "countries.division", "pk": 4127, "fields": {"country": "UY", "code": "FD", "name": "Florida", "alt_names": "[\"FLorida\"]", "location": "SRID=4326;POINT (-56.216667 -34.1)", "bbox": "SRID=4326;POLYGON ((-56.2453946 -34.1148295, -56.2453946 -34.0753834, -56.2004211 -34.0753834, -56.2004211 -34.1148295, -56.2453946 -34.1148295))"}}, {"model": "countries.division", "pk": 4128, "fields": {"country": "UY", "code": "FS", "name": "Flores", "alt_names": "[\"Flores\"]", "location": "SRID=4326;POINT (-56.8311117 -33.5629477)", "bbox": "SRID=4326;POLYGON ((-57.359303 -33.963974, -57.359303 -33.12822, -56.3974 -33.12822, -56.3974 -33.963974, -57.359303 -33.963974))"}}, {"model": "countries.division", "pk": 4129, "fields": {"country": "UY", "code": "LA", "name": "Lavalleja", "alt_names": "[\"Lavalleja\"]", "location": "SRID=4326;POINT (-54.9611836 -34.0040354)", "bbox": "SRID=4326;POLYGON ((-55.6264269 -34.6143989, -55.6264269 -33.296482, -54.126133 -33.296482, -54.126133 -34.6143989, -55.6264269 -34.6143989))"}}, {"model": "countries.division", "pk": 4130, "fields": {"country": "UY", "code": "MA", "name": "Maldonado", "alt_names": "[\"Maldonado\"]", "location": "SRID=4326;POINT (-54.9611836 -34.6277617)", "bbox": "SRID=4326;POLYGON ((-55.4849819 -34.9733882, -55.4849819 -33.9133488, -54.4719539 -33.9133488, -54.4719539 -34.9733882, -55.4849819 -34.9733882))"}}, {"model": "countries.division", "pk": 4131, "fields": {"country": "UY", "code": "MO", "name": "Montevideo", "alt_names": "[\"Montevideo\"]", "location": "SRID=4326;POINT (-56.1645314 -34.9011127)", "bbox": "SRID=4326;POLYGON ((-56.4311685 -34.9379555, -56.4311685 -34.70193, -56.0292436 -34.70193, -56.0292436 -34.9379555, -56.4311685 -34.9379555))"}}, {"model": "countries.division", "pk": 4132, "fields": {"country": "UY", "code": "PA", "name": "Paysand\u00fa", "alt_names": "[\"Paysand\\u00fa\"]", "location": "SRID=4326;POINT (-57.4627259 -32.2216595)", "bbox": "SRID=4326;POLYGON ((-58.205719 -32.572212, -58.205719 -31.4293369, -56.2413251 -31.4293369, -56.2413251 -32.572212, -58.205719 -32.572212))"}}, {"model": "countries.division", "pk": 4133, "fields": {"country": "UY", "code": "RN", "name": "R\u00edo Negro", "alt_names": "[\"R\\u00edo Negro\"]", "location": "SRID=4326;POINT (-57.1013188 -32.7625409)", "bbox": "SRID=4326;POLYGON ((-58.4203151 -33.4182849, -58.4203151 -32.3229219, -56.547501 -32.3229219, -56.547501 -33.4182849, -58.4203151 -33.4182849))"}}, {"model": "countries.division", "pk": 4134, "fields": {"country": "UY", "code": "RO", "name": "Rocha", "alt_names": "[\"Rocha\"]", "location": "SRID=4326;POINT (-53.9106594 -33.9674948)", "bbox": "SRID=4326;POLYGON ((-54.564964 -34.7936294, -54.564964 -33.1358951, -53.3785147 -33.1358951, -53.3785147 -34.7936294, -54.564964 -34.7936294))"}}, {"model": "countries.division", "pk": 4135, "fields": {"country": "UY", "code": "RV", "name": "Rivera", "alt_names": "[\"Rivera\"]", "location": "SRID=4326;POINT (-55.550556 -30.9025)", "bbox": "SRID=4326;POLYGON ((-55.6165266 -30.9871014, -55.6165266 -30.8566634, -55.4523149 -30.8566634, -55.4523149 -30.9871014, -55.6165266 -30.9871014))"}}, {"model": "countries.division", "pk": 4136, "fields": {"country": "UY", "code": "SA", "name": "Salto", "alt_names": "[\"Salto\"]", "location": "SRID=4326;POINT (-57.1013188 -31.4679335)", "bbox": "SRID=4326;POLYGON ((-58.0779601 -31.8470001, -58.0779601 -30.716536, -55.9999059 -30.716536, -55.9999059 -31.8470001, -58.0779601 -31.8470001))"}}, {"model": "countries.division", "pk": 4137, "fields": {"country": "UY", "code": "SJ", "name": "San Jos\u00e9", "alt_names": "[\"San Jos\\u00e9\"]", "location": "SRID=4326;POINT (-56.741207 -34.250223)", "bbox": "SRID=4326;POLYGON ((-57.1731299 -34.78946, -57.1731299 -33.816353, -56.343634 -33.816353, -56.343634 -34.78946, -57.1731299 -34.78946))"}}, {"model": "countries.division", "pk": 4138, "fields": {"country": "UY", "code": "SO", "name": "Soriano", "alt_names": "[\"Soriano\"]", "location": "SRID=4326;POINT (-57.7346113 -33.5103372)", "bbox": "SRID=4326;POLYGON ((-58.442722 -33.9466588, -58.442722 -33.006599, -57.0863759 -33.006599, -57.0863759 -33.9466588, -58.442722 -33.9466588))"}}, {"model": "countries.division", "pk": 4139, "fields": {"country": "UY", "code": "TA", "name": "Tacuaremb\u00f3", "alt_names": "[\"Tacuaremb\\u00f3\"]", "location": "SRID=4326;POINT (-55.6689636 -32.0106717)", "bbox": "SRID=4326;POLYGON ((-56.663515 -32.872563, -56.663515 -31.210968, -54.651097 -31.210968, -54.651097 -32.872563, -56.663515 -32.872563))"}}, {"model": "countries.division", "pk": 4140, "fields": {"country": "UY", "code": "TT", "name": "Treinta y Tres", "alt_names": "[\"Treinta y Tres\"]", "location": "SRID=4326;POINT (-54.2593118 -33.1476661)", "bbox": "SRID=4326;POLYGON ((-55.158798 -33.444572, -55.158798 -32.682854, -53.2823961 -32.682854, -53.2823961 -33.444572, -55.158798 -33.444572))"}}]