{
  "SystemType": "Card",
  "BoardId": 100000000,
  "BoardTitle": "Board 100000000",
  "LaneId": 100001004,
  "LaneTitle": "Sublane 2.1",
  "Title": "Task 2",
  "Description": null,
  "Type": {
    "Id": 100000015
  },
  "TypeId": 100000015,
  "Priority": 1,
  "PriorityText": "Normal",
  "TypeName": "Task",
  "TypeIconPath": null,
  "TypeColorHex": "#f5f2bc",
  "Size": 0,
  "Active": false,
  "Color": "#f5f2bc",
  "Icon": "",
  "Version": 9,
  "AssignedUsers": [
    {
      "Id": 100000001,
      "GravatarLink": "36020adab302af77eb6273e0b2ead7cf?s=25",
      "SmallGravatarLink": "36020adab302af77eb6273e0b2ead7cf?s=17",
      "EmailAddress": "User1@example.org",
      "FullName": "User 1",
      "AssignedUserName": "User 1",
      "AssignedUserId": 100000001
    }
  ],
  "IsBlocked": false,
  "BlockReason": null,
  "BlockStateChangeDate": null,
  "Index": 0,
  "StartDate": null,
  "DueDate": null,
  "ExternalSystemName": null,
  "ExternalSystemUrl": null,
  "ExternalCardID": null,
  "ExternalCardIdPrefix": "",
  "Tags": "Tag1,Tag2",
  "ParentBoardId": 0,
  "ParentBoardIds": [],
  "ParentTaskboardId": null,
  "CountOfOldCards": 0,
  "CardContexts": [],
  "LastMove": "03/15/2017 12:45:00 PM",
  "LastActivity": "03/15/2017 12:45:00 PM",
  "DateArchived": null,
  "CommentsCount": 1,
  "LastComment": "02/27/2017",
  "AttachmentsCount": 0,
  "LastAttachment": null,
  "CreateDate": "02/27/2017",
  "ActualStartDate": "2/27/2017 10:30:00 PM",
  "ActualFinishDate": null,
  "AssignedUserName": "User 1",
  "AssignedUserId": 100000001,
  "AssignedUserIds": [
    100000001
  ],
  "GravatarLink": "36020adab302af77eb6273e0b2ead7cf?s=25",
  "SmallGravatarLink": "36020adab302af77eb6273e0b2ead7cf?s=17",
  "IsOlderThanXDays": false,
  "Id": 100010001,
  "DrillThroughBoardId": null,
  "CardDrillThroughBoardIds": [],
  "HasDrillThroughBoard": false,
  "HasMultipleDrillThroughBoards": false,
  "DrillThroughStatistics": null,
  "DrillThroughCompletionPercent": null,
  "DrillThroughProgressTotal": null,
  "DrillThroughProgressComplete": null,
  "DrillThroughProgressSizeComplete": null,
  "DrillThroughProgressSizeTotal": null,
  "ClassOfServiceId": 0,
  "ClassOfServiceTitle": null,
  "ClassOfServiceIconPath": null,
  "ClassOfServiceColorHex": null,
  "ClassOfServiceCustomIconName": null,
  "ClassOfServiceCustomIconColor": null,
  "CardTypeIconColor": null,
  "CardTypeIconName": null,
  "CurrentTaskBoardId": null,
  "TaskBoardCompletionPercent": 0,
  "TaskBoardCompletedCardCount": 0,
  "TaskBoardCompletedCardSize": 0,
  "TaskBoardTotalCards": 0,
  "TaskBoardTotalSize": 0,
  "CurrentContext": null,
  "ParentCardId": null,
  "ParentCardIds": []
}
