{
    "name": "MyProject",
    "alias": "{{this.name.lower}}",
    "extensions": ".ngo, .pyproj",
    "parsers": "ngomodel.parsers.YamlParser, ngomodel.parsers.JsonParser",
    "serializers": [ "ngomodel.parsers.YamlParser" ],
    "version": "",
    "vsGuid": "",
    "authorName": "",
    "authorEmail": "__Email__",
    "website": "__Url__",
    "githubUrl": "__Url__",
    "docUrl": "__Url__",
    "gitRepo": "git@github.com:numengo//{{this.repoName}}.git",
    "repoName": "{{ this.type }}-{{ this.name|lower|replace(' ','-') }}",
    "packageName": "{{ this.name|lower|replace(' ','_')|replace('-','_') }}",
    "distributionName": "{{ this.packageName|replace('_','-') }}",
    "description": "",
    "shortDescription": "",
    "keywords": [],
    "license": [ "GNU General Public License v3", "NUMENGO", "BSD 2-Clause License", "BSD 3-Clause License", "MIT license", "ISC license", "Apache Software License 2.0" ],
    "lic": "",
    "releaseDate": "__Date__",
    "dev_status": [ "Alpha", "Beta", "Production/Stable", "Mature" ],
    "type": [ "python", "django-plugin", "django-app", "django-cms", "cpp", "sim" ],
    "isPython3": true,
    "isClient": false,
    "hasTest": false,
    "pythonSupport": [],
    "djangoSupport": [],
    "djangoCmsSupport": [],
    "deps": [],
    "entryPoints": [],
    "pythonEnvs": { "": "ngomodel.parsers.YamlParser" },
    "toxEnv": "ngomodel.parsers.YamlParser",
    "setup_py": "__ExistingPath__",
    "repoDir": "__ExistingPath__",
    "projectDir": "__ExistingPath__",
    "tox_ini": "__ExistingPath__",
    "envVar": "DirProject{{this.name}}Root",
    "fileSrcManager": "ngomodel.parsers.YamlParser",
    "fileDataManager": "ngomodel.parsers.YamlParser",
    "fileTestManager": "ngomodel.parsers.YamlParser"
}
