[{"model": "countries.countryname", "pk": 696, "fields": {"country": "CI", "language": "deu", "common": "Elfenbeink\u00fcste", "official": "Republik C\u00f4te d'Ivoire"}}, {"model": "countries.countryname", "pk": 709, "fields": {"country": "CI", "language": "eng", "common": "Ivory Coast", "official": "Republic of C\u00f4te d'Ivoire"}}, {"model": "countries.countryname", "pk": 707, "fields": {"country": "CI", "language": "est", "common": "Elevandiluurannik", "official": "C\u00f4te d\u2019Ivoire\u2019i Vabariik"}}, {"model": "countries.countryname", "pk": 706, "fields": {"country": "CI", "language": "fin", "common": "Norsunluurannikko", "official": "Norsunluurannikon tasavalta"}}, {"model": "countries.countryname", "pk": 697, "fields": {"country": "CI", "language": "fra", "common": "C\u00f4te d'Ivoire", "official": "R\u00e9publique de C\u00f4te d'Ivoire"}}, {"model": "countries.countryname", "pk": 698, "fields": {"country": "CI", "language": "hrv", "common": "Obala Bjelokosti", "official": "Republika C\u00f4te d'Ivoire"}}, {"model": "countries.countryname", "pk": 699, "fields": {"country": "CI", "language": "ita", "common": "Costa d'Avorio", "official": "Repubblica della Costa d'Avorio"}}, {"model": "countries.countryname", "pk": 700, "fields": {"country": "CI", "language": "jpn", "common": "\u30b3\u30fc\u30c8\u30b8\u30dc\u30ef\u30fc\u30eb", "official": "\u30b3\u30fc\u30c8\u30b8\u30dc\u30ef\u30fc\u30eb\u5171\u548c\u56fd"}}, {"model": "countries.countryname", "pk": 701, "fields": {"country": "CI", "language": "nld", "common": "Ivoorkust", "official": "Republiek Ivoorkust"}}, {"model": "countries.countryname", "pk": 702, "fields": {"country": "CI", "language": "por", "common": "Costa do Marfim", "official": "Rep\u00fablica da C\u00f4te d'Ivoire"}}, {"model": "countries.countryname", "pk": 703, "fields": {"country": "CI", "language": "rus", "common": "\u041a\u043e\u0442-\u0434\u2019\u0418\u0432\u0443\u0430\u0440", "official": "\u0420\u0435\u0441\u043f\u0443\u0431\u043b\u0438\u043a\u0430 \u041a\u043e\u0442-\u0434'\u0418\u0432\u0443\u0430\u0440\u0435"}}, {"model": "countries.countryname", "pk": 704, "fields": {"country": "CI", "language": "slk", "common": "Pobr\u017eie Slonoviny", "official": "Republika Pobre\u017eie Slonoviny"}}, {"model": "countries.countryname", "pk": 705, "fields": {"country": "CI", "language": "spa", "common": "Costa de Marfil", "official": "Rep\u00fablica de C\u00f4te d'Ivoire"}}, {"model": "countries.countryname", "pk": 708, "fields": {"country": "CI", "language": "zho", "common": "\u79d1\u7279\u8fea\u74e6", "official": "\u79d1\u7279\u8fea\u74e6\u5171\u548c\u56fd"}}]