[{"model": "countries.countryname", "pk": 959, "fields": {"country": "DM", "language": "cym", "common": "Dominica", "official": "Cymanwlad Dominica"}}, {"model": "countries.countryname", "pk": 960, "fields": {"country": "DM", "language": "deu", "common": "Dominica", "official": "Commonwealth von Dominica"}}, {"model": "countries.countryname", "pk": 973, "fields": {"country": "DM", "language": "eng", "common": "Dominica", "official": "Commonwealth of Dominica"}}, {"model": "countries.countryname", "pk": 971, "fields": {"country": "DM", "language": "est", "common": "Dominica", "official": "Dominica \u00dchendus"}}, {"model": "countries.countryname", "pk": 970, "fields": {"country": "DM", "language": "fin", "common": "Dominica", "official": "Dominican liittovaltio"}}, {"model": "countries.countryname", "pk": 961, "fields": {"country": "DM", "language": "fra", "common": "Dominique", "official": "Commonwealth de la Dominique"}}, {"model": "countries.countryname", "pk": 962, "fields": {"country": "DM", "language": "hrv", "common": "Dominika", "official": "Zajednica Dominika"}}, {"model": "countries.countryname", "pk": 963, "fields": {"country": "DM", "language": "ita", "common": "Dominica", "official": "Commonwealth di Dominica"}}, {"model": "countries.countryname", "pk": 964, "fields": {"country": "DM", "language": "jpn", "common": "\u30c9\u30df\u30cb\u30ab\u56fd", "official": "\u30c9\u30df\u30cb\u30ab\u56fd"}}, {"model": "countries.countryname", "pk": 965, "fields": {"country": "DM", "language": "nld", "common": "Dominica", "official": "Gemenebest Dominica"}}, {"model": "countries.countryname", "pk": 966, "fields": {"country": "DM", "language": "por", "common": "Dominica", "official": "Comunidade da Dominica"}}, {"model": "countries.countryname", "pk": 967, "fields": {"country": "DM", "language": "rus", "common": "\u0414\u043e\u043c\u0438\u043d\u0438\u043a\u0430", "official": "\u0421\u043e\u0434\u0440\u0443\u0436\u0435\u0441\u0442\u0432\u043e \u0414\u043e\u043c\u0438\u043d\u0438\u043a\u0438"}}, {"model": "countries.countryname", "pk": 968, "fields": {"country": "DM", "language": "slk", "common": "Dominika", "official": "Dominick\u00e9 spolo\u010denstvo"}}, {"model": "countries.countryname", "pk": 969, "fields": {"country": "DM", "language": "spa", "common": "Dominica", "official": "Mancomunidad de Dominica"}}, {"model": "countries.countryname", "pk": 972, "fields": {"country": "DM", "language": "zho", "common": "\u591a\u7c73\u5c3c\u52a0", "official": "\u591a\u7c73\u5c3c\u52a0\u5171\u548c\u56fd"}}]