[{"model": "countries.division", "pk": 4355, "fields": {"country": "ZM", "code": "01", "name": "Western", "alt_names": "[\"Western\"]", "location": "SRID=4326;POINT (23.3823545 -15.9454906)", "bbox": "SRID=4326;POLYGON ((21.999371 -17.6392799, 21.999371 -13.709041, 25.52071 -13.709041, 25.52071 -17.6392799, 21.999371 -17.6392799))"}}, {"model": "countries.division", "pk": 4356, "fields": {"country": "ZM", "code": "02", "name": "Central", "alt_names": "[\"Central\"]", "location": "SRID=4326;POINT (28.299435 -14.3112263)", "bbox": "SRID=4326;POLYGON ((25.350383 -15.7121141, 25.350383 -12.0036589, 31.4494591 -12.0036589, 31.4494591 -15.7121141, 25.350383 -15.7121141))"}}, {"model": "countries.division", "pk": 4357, "fields": {"country": "ZM", "code": "03", "name": "Eastern", "alt_names": "[\"Eastern\"]", "location": "SRID=4326;POINT (31.9928078 -13.8056187)", "bbox": "SRID=4326;POLYGON ((29.9865299 -14.997233, 29.9865299 -10.3251301, 33.6895011 -10.3251301, 33.6895011 -14.997233, 29.9865299 -14.997233))"}}, {"model": "countries.division", "pk": 4358, "fields": {"country": "ZM", "code": "04", "name": "Luapula", "alt_names": "[\"Luapula\"]", "location": "SRID=4326;POINT (29.0459927 -11.564831)", "bbox": "SRID=4326;POLYGON ((28.3809699 -12.471966, 28.3809699 -8.375692900000001, 30.466128 -8.375692900000001, 30.466128 -12.471966, 28.3809699 -12.471966))"}}, {"model": "countries.division", "pk": 4359, "fields": {"country": "ZM", "code": "05", "name": "Northern", "alt_names": "[\"Northern\"]", "location": "SRID=4326;POINT (30.8958242 -9.7670177)", "bbox": "SRID=4326;POLYGON ((29.10338 -13.4275721, 29.10338 -8.251887, 33.705704 -8.251887, 33.705704 -13.4275721, 29.10338 -13.4275721))"}}, {"model": "countries.division", "pk": 4360, "fields": {"country": "ZM", "code": "06", "name": "North-Western", "alt_names": "[\"North-Western\"]", "location": "SRID=4326;POINT (24.9042208 -13.0050258)", "bbox": "SRID=4326;POLYGON ((21.999899 -14.72759, 21.999899 -10.885152, 27.6016581 -10.885152, 27.6016581 -14.72759, 21.999899 -14.72759))"}}, {"model": "countries.division", "pk": 4361, "fields": {"country": "ZM", "code": "07", "name": "Southern", "alt_names": "[\"Southern\"]", "location": "SRID=4326;POINT (26.419389 -16.9620634)", "bbox": "SRID=4326;POLYGON ((24.9715499 -18.079473, 24.9715499 -15.293982, 28.912453 -15.293982, 28.912453 -18.079473, 24.9715499 -18.079473))"}}, {"model": "countries.division", "pk": 4362, "fields": {"country": "ZM", "code": "08", "name": "Copperbelt", "alt_names": "[\"Copperbelt\"]", "location": "SRID=4326;POINT (27.5495846 -13.0570073)", "bbox": "SRID=4326;POLYGON ((26.801156 -13.9245529, 26.801156 -12.218456, 29.0201341 -12.218456, 29.0201341 -13.9245529, 26.801156 -13.9245529))"}}, {"model": "countries.division", "pk": 4363, "fields": {"country": "ZM", "code": "09", "name": "Lusaka", "alt_names": "[\"Lusaka\"]", "location": "SRID=4326;POINT (28.283333 -15.416667)", "bbox": "SRID=4326;POLYGON ((28.1987555 -15.5344065, 28.1987555 -15.2992532, 28.4887506 -15.2992532, 28.4887506 -15.5344065, 28.1987555 -15.5344065))"}}]